otah.py
otah-0.1.1.dist-info/entry_points.txt
otah-0.1.1.dist-info/LICENSE
otah-0.1.1.dist-info/WHEEL
otah-0.1.1.dist-info/METADATA
otah-0.1.1.dist-info/RECORD
