Metadata-Version: 2.1
Name: otah
Version: 0.1.1
Summary: create OTA manifests from iOS .ipa files for distribution outside the App Store.
Home-page: https://github.com/ongyx/otah
License: UNKNOWN
Author: Ong Yong Xin
Author-email: ongyongxin2020+github@gmail.com
Requires-Python: >=3.6
Classifier: Programming Language :: Python :: 3
Classifier: License :: OSI Approved :: Apache Software License
Classifier: Operating System :: OS Independent
